osnapi/__init__.py
osnapi/_nbdev.py
osnapi/core.py
osnapi-0.0.1.dist-info/LICENSE
osnapi-0.0.1.dist-info/METADATA
osnapi-0.0.1.dist-info/WHEEL
osnapi-0.0.1.dist-info/entry_points.txt
osnapi-0.0.1.dist-info/top_level.txt
osnapi-0.0.1.dist-info/RECORD
