Metadata-Version: 2.1
Name: osnapi
Version: 0.0.1
Summary: unofficial opensense.network api
Home-page: https://github.com/flpeters/osnapi/tree/master/
Author: Florian Peters
Author-email: 38505891+flpeters@users.noreply.github.com
License: Apache Software License 2.0
Keywords: python,web-api
Platform: UNKNOWN
Classifier: Development Status :: 6 - Mature
Classifier: Intended Audience :: Developers
Classifier: License :: OSI Approved :: Apache Software License
Classifier: Natural Language :: English
Classifier: Programming Language :: Python :: 3.6
Classifier: Programming Language :: Python :: 3.7
Classifier: Programming Language :: Python :: 3.8
Requires-Python: >=3.6
Requires-Dist: requests (>=2.22.0)
